<?xml version="1.0" encoding="UTF-8"?>
<MetaDataObject xmlns="http://v8.1c.ru/8.3/MDClasses" xmlns:app="http://v8.1c.ru/8.2/managed-application/core" xmlns:cfg="http://v8.1c.ru/8.1/data/enterprise/current-config" xmlns:cmi="http://v8.1c.ru/8.2/managed-application/cmi" xmlns:ent="http://v8.1c.ru/8.1/data/enterprise" xmlns:lf="http://v8.1c.ru/8.2/managed-application/logform" xmlns:style="http://v8.1c.ru/8.1/data/ui/style" xmlns:sys="http://v8.1c.ru/8.1/data/ui/fonts/system" xmlns:v8="http://v8.1c.ru/8.1/data/core" xmlns:v8ui="http://v8.1c.ru/8.1/data/ui" xmlns:web="http://v8.1c.ru/8.1/data/ui/colors/web" xmlns:win="http://v8.1c.ru/8.1/data/ui/colors/windows" xmlns:xen="http://v8.1c.ru/8.3/xcf/enums" xmlns:xpr="http://v8.1c.ru/8.3/xcf/predef" xmlns:xr="http://v8.1c.ru/8.3/xcf/readable" xmlns:xs="http://www.w3.org/2001/XMLSchema" xmlns:xsi="http://www.w3.org/2001/XMLSchema-instance">
	<Enum uuid="b6cff1cd-a4c4-4e66-b5f7-f34ac68c4270">
		<InternalInfo>
			<xr:GeneratedType name="EnumRef.ТипыТипов" category="Ref">
				<xr:TypeId>f3c0cae7-dc3c-4e25-a020-fc2023e35f86</xr:TypeId>
				<xr:ValueId>ed1f56c6-3c27-4b33-aaa5-addfacf7c07c</xr:ValueId>
			</xr:GeneratedType>
			<xr:GeneratedType name="EnumManager.ТипыТипов" category="Manager">
				<xr:TypeId>54ba1801-29c7-485e-8d4a-17d8121d84ae</xr:TypeId>
				<xr:ValueId>6b63ff7f-627a-4620-b2ab-7d8d2b5ba7fc</xr:ValueId>
			</xr:GeneratedType>
			<xr:GeneratedType name="EnumList.ТипыТипов" category="List">
				<xr:TypeId>3b6da1e8-44a9-46df-9491-b329c8f7a5b0</xr:TypeId>
				<xr:ValueId>321e8d4e-70b5-4da3-95fd-770a6454fe2a</xr:ValueId>
			</xr:GeneratedType>
		</InternalInfo>
		<Properties>
			<Name>ТипыТипов</Name>
			<Synonym>
				<v8:item>
					<v8:lang>ru</v8:lang>
					<v8:content>Типы типов</v8:content>
				</v8:item>
			</Synonym>
			<Comment/>
			<UseStandardCommands>false</UseStandardCommands>
			<Characteristics/>
			<QuickChoice>true</QuickChoice>
			<ChoiceMode>BothWays</ChoiceMode>
			<DefaultListForm/>
			<DefaultChoiceForm/>
			<AuxiliaryListForm/>
			<AuxiliaryChoiceForm/>
			<ListPresentation/>
			<ExtendedListPresentation/>
			<Explanation/>
			<ChoiceHistoryOnInput>Auto</ChoiceHistoryOnInput>
		</Properties>
		<ChildObjects>
			<EnumValue uuid="84ea10d4-affe-4df4-a2aa-3a15e6aa0f7a">
				<Properties>
					<Name>Перечисление</Name>
					<Synonym>
						<v8:item>
							<v8:lang>ru</v8:lang>
							<v8:content>Перечисление</v8:content>
						</v8:item>
					</Synonym>
					<Comment/>
				</Properties>
			</EnumValue>
			<EnumValue uuid="f9c176a9-fcea-4848-ba9d-be476087d9fb">
				<Properties>
					<Name>Объект</Name>
					<Synonym>
						<v8:item>
							<v8:lang>ru</v8:lang>
							<v8:content>Объект</v8:content>
						</v8:item>
					</Synonym>
					<Comment/>
				</Properties>
			</EnumValue>
		</ChildObjects>
	</Enum>
</MetaDataObject>